LIBTwinSVM-0.3.0.dist-info/WHEEL
LIBTwinSVM-0.3.0.dist-info/top_level.txt
LIBTwinSVM-0.3.0.dist-info/METADATA
LIBTwinSVM-0.3.0.dist-info/RECORD
libtsvm/setup.py
libtsvm/app.py
libtsvm/preprocess.py
libtsvm/__main__.py
libtsvm/__init__.py
libtsvm/model_eval.py
libtsvm/visualize.py
libtsvm/misc.py
libtsvm/model_selection.py
libtsvm/mc_scheme.py
libtsvm/estimators.py
libtsvm/model.py
libtsvm/optimizer/setup.py
libtsvm/optimizer/clipdcd.cpython-35m-x86_64-linux-gnu.so
libtsvm/optimizer/__init__.py
libtsvm/ui/icons_rc.py
libtsvm/ui/__init__.py
libtsvm/ui/about_diag.py
libtsvm/ui/confirm_diag.py
libtsvm/ui/gui.py
libtsvm/ui/view.py
libtsvm/.libs/liblapack-78e59728.so.3.0.3
libtsvm/.libs/libgfortran-bfa58d52.so.1.0.0
libtsvm/.libs/libblas-2d5b9174.so.3.0.3
